mpris_server/__init__.py
mpris_server/adapters.py
mpris_server/base.py
mpris_server/enums.py
mpris_server/events.py
mpris_server/py.typed
mpris_server/server.py
mpris_server/types.py
mpris_server/interfaces/__init__.py
mpris_server/interfaces/interface.py
mpris_server/interfaces/player.py
mpris_server/interfaces/playlists.py
mpris_server/interfaces/root.py
mpris_server/interfaces/tracklist.py
mpris_server/mpris/__init__.py
mpris_server/mpris/compat.py
mpris_server/mpris/metadata.py
mpris_server-0.9.6.dist-info/LICENSE
mpris_server-0.9.6.dist-info/METADATA
mpris_server-0.9.6.dist-info/NOTICE
mpris_server-0.9.6.dist-info/WHEEL
mpris_server-0.9.6.dist-info/top_level.txt
mpris_server-0.9.6.dist-info/zip-safe
mpris_server-0.9.6.dist-info/RECORD
