Metadata-Version: 2.1
Name: mpris_server
Version: 0.9.6
Summary: ⏯️ Publish a MediaPlayer2 MPRIS device to D-Bus.
Home-page: https://github.com/alexdelorenzo/mpris_server
Author: Alex DeLorenzo <alex@alexdelorenzo.dev>
License: License :: OSI Approved :: LGPL-3.0-only
Requires-Python: >=3.12
License-File: LICENSE
License-File: NOTICE
Requires-Dist: emoji<3.0.0,>=2.8.0
Requires-Dist: pydbus<0.7.0,>=0.6.0
Requires-Dist: PyGObject>=3.34.0
Requires-Dist: StrEnum>=0.4.15
Requires-Dist: unidecode<2.0.0,>=1.3.7
